gumo/__init__.py
gumo/datastore/__init__.py
gumo/datastore/_bind.py
gumo/datastore/_configuration.py
gumo/datastore/domain/__init__.py
gumo/datastore/domain/configuration/__init__.py
gumo/datastore/infrastructure/__init__.py
gumo/datastore/infrastructure/alias.py
gumo/datastore/infrastructure/configuration/__init__.py
gumo/datastore/infrastructure/entity_key_mapper/__init__.py
gumo/datastore/infrastructure/key_id_allocator/__init__.py
gumo/datastore/infrastructure/mapper/__init__.py
gumo/datastore/infrastructure/model/__init__.py
gumo/datastore/infrastructure/repository/__init__.py
gumo/datastore/infrastructure/test_utils/__init__.py
gumo_datastore-0.2.0.dist-info/LICENSE
gumo_datastore-0.2.0.dist-info/METADATA
gumo_datastore-0.2.0.dist-info/WHEEL
gumo_datastore-0.2.0.dist-info/top_level.txt
gumo_datastore-0.2.0.dist-info/RECORD
