Metadata-Version: 2.1
Name: gumo-datastore
Version: 0.2.0
Summary: Gumo Datastore Library
Home-page: https://github.com/gumo-py/gumo-datastore
Author: Gumo Project Team
Author-email: gumo-py@googlegroups.com
License: UNKNOWN
Platform: UNKNOWN
Classifier: Programming Language :: Python :: 3
Classifier: License :: OSI Approved :: MIT License
Classifier: Operating System :: OS Independent
Requires-Dist: gumo-core (>=0.1.3)
Requires-Dist: google-cloud-datastore (>=1.15.0)
